pyEPR/__config_user_old.py
pyEPR/__init__.py
pyEPR/_config_default.py
pyEPR/_config_user.py
pyEPR/ansys.py
pyEPR/core.py
pyEPR/core_distributed_analysis.py
pyEPR/core_quantum_analysis.py
pyEPR/project_info.py
pyEPR/reports.py
pyEPR/calcs/__init__.py
pyEPR/calcs/back_box_numeric.py
pyEPR/calcs/basic.py
pyEPR/calcs/constants.py
pyEPR/calcs/convert.py
pyEPR/calcs/hamiltonian.py
pyEPR/calcs/quantum.py
pyEPR/calcs/transmon.py
pyEPR/toolbox/__init__.py
pyEPR/toolbox/_logging.py
pyEPR/toolbox/plotting.py
pyEPR/toolbox/pythonic.py
pyEPR_quantum-0.8.5.7.dist-info/LICENSE
pyEPR_quantum-0.8.5.7.dist-info/METADATA
pyEPR_quantum-0.8.5.7.dist-info/WHEEL
pyEPR_quantum-0.8.5.7.dist-info/top_level.txt
pyEPR_quantum-0.8.5.7.dist-info/RECORD
