Metadata-Version: 2.1
Name: pyEPR-quantum
Version: 0.8.5.7
Home-page: https://github.com/zlatko-minev/pyEPR
Author: Zlatko K. Minev
Author-email: zlatko.minev@aya.yale.edu
Maintainer: Zlatko Minev, pyEPR team
License: BSD-3-Clause
Classifier: Intended Audience :: Developers
Classifier: Intended Audience :: Science/Research
Classifier: Operating System :: Microsoft :: Windows
Classifier: Operating System :: MacOS
Classifier: Operating System :: POSIX :: Linux
Classifier: Programming Language :: Python :: 3 :: Only
Classifier: Programming Language :: Python :: 3.5
Classifier: Programming Language :: Python :: 3.6
Classifier: Programming Language :: Python :: 3.7
Classifier: Programming Language :: Python :: 3.8
Classifier: Programming Language :: Python :: 3.9
Classifier: Programming Language :: Python :: 3.10
Classifier: Topic :: Scientific/Engineering
Classifier: Environment :: Console
Classifier: License :: OSI Approved :: Apache Software License
Requires-Python: >=3.5, <4
License-File: LICENSE
Requires-Dist: addict
Requires-Dist: numpy (>=1.15.0)
Requires-Dist: pandas (>=1.0.1)
Requires-Dist: matplotlib (>=3.1.0)
Requires-Dist: scipy (>=1.3.0)
Requires-Dist: xarray (>=0.10.0)
Requires-Dist: sympy (>=1.3)
Requires-Dist: sphinx-rtd-theme (>=0.4.0)
Requires-Dist: pint (>=0.8)
Requires-Dist: qutip (>=3.5.0)
Requires-Dist: ipython (>=7.0.0)
Requires-Dist: seaborn (>=0.10.0)
